ssa3021x/__init__.py
ssa3021x/ssa3021x.py
pyssa3021x_tspspi-0.0.3.dist-info/LICENSE.md
pyssa3021x_tspspi-0.0.3.dist-info/METADATA
pyssa3021x_tspspi-0.0.3.dist-info/WHEEL
pyssa3021x_tspspi-0.0.3.dist-info/top_level.txt
pyssa3021x_tspspi-0.0.3.dist-info/RECORD
