Metadata-Version: 2.1
Name: pyssa3021x-tspspi
Version: 0.0.3
Summary: Unofficial control library for SSA3021X spectrum analyzer
Home-page: https://github.com/tspspi/pyssa3021x
Author: Thomas Spielauer
Author-email: pypipackages01@tspi.at
Classifier: Programming Language :: Python :: 3
Classifier: License :: OSI Approved :: BSD License
Classifier: Operating System :: OS Independent
Requires-Python: >=3.6
License-File: LICENSE.md
Requires-Dist: pylabdevs-tspspi>=0.0.11
